{
  "globalStyle": "mb-4 leading-tight",
  "sizeStyles": {
    "h1": "text-4xl",
    "h2": "text-3xl",
    "h3": "text-2xl",
    "h4": "text-xl",
    "h5": "text-lg",
    "h6": "text-base"
  },
  "variants": {
    "default": "text-[theme(--ma-nautic-blue)]",
    "ma_nautic_section_drop": "font-['Vibur'] text-[theme(--ma-nautic-gold)] text-ma-heading",
    "ma_nautic_main_title": "font-[theme(--ma-nautic-font-display)] text-[theme(--ma-nautic-beige)] text-5xl md:text-6xl lg:text-7xl mb-4 tracking-wide",
    "ma_nautic_subtitle": "font-script text-white text-3xl md:text-4xl lg:text-5xl italic",
    "ma_nautic_section_subtitle": "font-['Roboto'] font-ma-black text-[theme(--ma-nautic-gold)] text-ma-subtitle mb-4 tracking-wide",
    "ma_nautic_section_title": "font-['Roboto'] font-ma-bold text-[theme(--ma-nautic-blue)] text-ma-title",
    "ma_nautic_section_title_white": "font-['Roboto'] font-ma-bold text-[theme(--ma-nautic-white)] text-ma-title",
    "ma_nautic_subtitle_light": "font-['Roboto'] font-ma-bold text-[theme(--ma-nautic-white)] text-ma-title",
    "ma_nautic_subtitle_boat": "font-['Roboto'] font-ma-bold text-[theme(--ma-nautic-blue)]text-ma-title",
    "section_title": "ma-nautic-section-title",
    "boat-title": "ma-nautic-boat-title",
    "hero": "ma-nautic-hero-heading"
  },
  "iconStyles": {
    "default": "text-[theme(--ma-nautic-teal)] inline-flex items-center mr-2"
  },
  "headings": [
    {
      "name": "home_h1",
      "level": 1,
      "text": "LOCATION DE BATEAU A SAINT-FLORENT, AVEC M.A NAUTIC",
      "style": "ma_nautic_section_drop"
    },
    {
      "name": "home_about_h2",
      "level": 2,
      "text": "Une agence locale et de proximité",
      "style": "ma_nautic_section_title"
    },
    {
      "name": "home_about_h3_team",
      "level": 3,
      "text": "Une équipe passionnée et disponible",
      "style": "ma_nautic_section_subtitle"
    },
    {
      "name": "home_about_h3_expert",
      "level": 3,
      "text": "Une expertise locale",
      "style": "ma_nautic_section_subtitle"
    },
    {
      "name": "home_discover_h2",
      "level": 2,
      "text": "Pourquoi louer un bateau à Saint-Florent ?",
      "style": "ma_nautic_section_title_white"
    },
    {
      "name": "home_discover_h3_desert",
      "level": 3,
      "text": "Explorer le désert des Agriates par la mer",
      "style": "ma_nautic_section_subtitle"
    },
    {
      "name": "home_discover_h3_cap",
      "level": 3,
      "text": "Découvrir le Cap Corse autrement",
      "style": "ma_nautic_section_subtitle"
    },
    {
      "name": "home_services_h2",
      "level": 2,
      "text": "Nos services de location de bateaux en Haute-Corse",
      "style": "ma_nautic_section_title"
    },
    {
      "name": "home_services_h3_licence",
      "level": 3,
      "text": "Prenez le large, avec ou sans permis",
      "style": "ma_nautic_section_subtitle"
    },
    {
      "name": "home_services_h3_group",
      "level": 3,
      "text": "Une flotte performante, adaptée à tous les groupes",
      "style": "ma_nautic_section_subtitle"
    },
    {
      "name": "home_custom_h2",
      "level": 2,
      "text": "Activités nautiques et services personnalisés pour votre journée en mer",
      "style": "ma_nautic_section_title"
    },
    {
      "name": "home_program_h2",
      "level": 2,
      "text": "Excursions en mer depuis Saint-Florent, pour découvrir la côte autrement",
      "style": "ma_nautic_section_title"
    },
    {
      "name": "boat_h1",
      "level": 1,
      "text": "LOCATION DE BATEAUX RIGIDES ET SEMI-RIGIDES EN CORSE",
      "style": "ma_nautic_section_drop"
    },
    {
      "name": "boat_hero_h2",
      "level": 2,
      "text": "Une flotte complète et entretenue pour explorer la Haute-Corse",
      "style": "ma_nautic_section_title"
    },
    {
      "name": "boat_hero_h3_free",
      "level": 3,
      "text": "Naviguez librement depuis Saint-Florent",
      "style": "ma_nautic_section_subtitle"
    },
    {
      "name": "boat_hero_h3_licence",
      "level": 3,
      "text": "Avec ou sans permis bateau : choisissez votre façon de naviguer",
      "style": "ma_nautic_section_subtitle"
    },
    {
      "name": "boat_info_h2",
      "level": 2,
      "text": "Nos bateaux à louer",
      "style": "ma_nautic_section_title"
    },
    {
      "name": "boat_customer_h2",
      "level": 2,
      "text": "À qui s’adresse la location de bateau avec M.A Nautic ?",
      "style": "ma_nautic_section_title"
    },
    {
      "name": "boat_info_h3_price",
      "level": 3,
      "text": "Tarifs et conditions de location",
      "style": "ma_nautic_section_subtitle"
    },
    {
      "name": "boat_info_h3_option",
      "level": 3,
      "text": "Options disponibles pour enrichir votre sortie",
      "style": "ma_nautic_section_subtitle"
    },
    {
      "name": "boat_whyus_h2",
      "level": 2,
      "text": "Pourquoi choisir MA-Nautic pour louer un bateau en Corse ?",
      "style": "ma_nautic_section_title"
    },
    {
      "name": "boat_whyus_h3_place",
      "level": 3,
      "text": "Une base idéale à Saint-Florent",
      "style": "ma_nautic_section_subtitle"
    },
    {
      "name": "boat_whyus_h3_spots",
      "level": 3,
      "text": "À découvrir au départ de nos bateaux",
      "style": "ma_nautic_section_subtitle"
    },
    {
      "name": "spot_h1",
      "level": 1,
      "text": "EXCURSION EN BATEAU À SAINT-FLORENT",
      "style": "ma_nautic_section_drop"
    },
    {
      "name": "spot_hero_h2",
      "level": 2,
      "text": "Le désert des Agriates par la mer : plages secrètes et escales gourmandes",
      "style": "ma_nautic_section_title"
    },
    {
      "name": "spot_capcorse_h2",
      "level": 2,
      "text": "Le Cap Corse : falaises, villages perchés et cuisine marine",
      "style": "ma_nautic_section_title"
    },
    {
      "name": "spot_manautic_h2",
      "level": 2,
      "text": "M.A Nautic : votre embarcation vers les plus beaux sites de Haute-Corse",
      "style": "ma_nautic_section_title"
    },
    {
      "name": "spot_manautic_h3_stflorent",
      "level": 3,
      "text": "Les lieux incontournables à découvrir depuis Saint-Florent",
      "style": "ma_nautic_section_subtitle"
    },
    {
      "name": "spot_manautic_h3_trust",
      "level": 3,
      "text": "M.A Nautic, pour une navigation de confiance",
      "style": "ma_nautic_section_subtitle"
    },
    {
      "name": "contact_h1",
      "level": 1,
      "text": "INFORMATIONS ET COORDONNÉES : CONTACTEZ M.A NAUTIC",
      "style": "ma_nautic_section_drop"
    },
    {
      "name": "contact_hero_h2",
      "level": 2,
      "text": "Contactez notre agence de location de bateaux à en Haute-Corse",
      "style": "ma_nautic_section_title"
    },
    {
      "name": "contact_access_h2",
      "level": 2,
      "text": "Accès à M.A Nautic à Saint Florent",
      "style": "ma_nautic_section_title"
    },
    {
      "name": "contact_access_h3_details",
      "level": 3,
      "text": "Toutes nos coordonnées",
      "style": "ma_nautic_section_subtitle"
    },
    {
      "name": "faq_h1",
      "level": 1,
      "text": "LOUER UN BATEAU EN CORSE AVEC MA NAUTIC : TOUTES VOS QUESTIONS",
      "style": "ma_nautic_section_drop"
    },
    {
      "name": "faq_intro_h2",
      "level": 2,
      "text": "Louer un bateau en Corse : pourquoi choisir Saint-Florent ?",
      "style": "ma_nautic_section_title"
    },
    {
      "name": "faq_location_h2",
      "level": 2,
      "text": "Questions fréquentes sur la location de bateau à Saint-Florent",
      "style": "ma_nautic_section_title"
    },
    {
      "name": "faq_location_h3_functioning",
      "level": 3,
      "text": "Comment fonctionne la location de bateau chez MA Nautic ?",
      "style": "ma_nautic_section_subtitle"
    },
    {
      "name": "faq_location_h3_steps",
      "level": 3,
      "text": "Quelles sont les étapes pour réserver un bateau à Saint-Florent ?",
      "style": "ma_nautic_section_subtitle"
    },
    {
      "name": "faq_location_h3_licence",
      "level": 3,
      "text": "Faut-il un permis pour louer un bateau en Haute-Corse ?",
      "style": "ma_nautic_section_subtitle"
    },
    {
      "name": "faq_location_h3_nolicence",
      "level": 3,
      "text": "Peut-on louer un bateau sans permis en Haute-Corse ?",
      "style": "ma_nautic_section_subtitle"
    },
    {
      "name": "faq_location_h3_parking",
      "level": 3,
      "text": "Où se trouve MA Nautic et peut-on s’y garer facilement ?",
      "style": "ma_nautic_section_subtitle"
    },
    {
      "name": "faq_location_h3_security",
      "level": 3,
      "text": "Les bateaux sont-ils bien armés pour la navigation ?",
      "style": "ma_nautic_section_subtitle"
    },
    {
      "name": "faq_conditions_h2",
      "level": 2,
      "text": "Conditions météo, sécurité et carburant",
      "style": "ma_nautic_section_title"
    },
    {
      "name": "faq_conditions_h3_weather",
      "level": 3,
      "text": "Que se passe-t-il en cas de météo défavorable ?",
      "style": "ma_nautic_section_subtitle"
    },
    {
      "name": "faq_conditions_h3_refund",
      "level": 3,
      "text": "La location est-elle remboursée en cas de mauvais temps ?",
      "style": "ma_nautic_section_subtitle"
    },
    {
      "name": "faq_conditions_h3_gasoline",
      "level": 3,
      "text": "Où faire le plein d’essence à Saint-Florent ?",
      "style": "ma_nautic_section_subtitle"
    },
    {
      "name": "faq_conditions_h3_security",
      "level": 3,
      "text": "Les équipements de sécurité sont-ils fournis à bord ?",
      "style": "ma_nautic_section_subtitle"
    },
    {
      "name": "faq_explore_h2",
      "level": 2,
      "text": "Explorer la Méditerranée : Saleccia, Lotu et les Agriates",
      "style": "ma_nautic_section_title"
    },
    {
      "name": "faq_explore_h3_saleccia",
      "level": 3,
      "text": "Comment rejoindre la plage de Saleccia en bateau ?",
      "style": "ma_nautic_section_subtitle"
    },
    {
      "name": "faq_explore_h3_distance",
      "level": 3,
      "text": "Quelle distance entre le Lotu et Saleccia ?",
      "style": "ma_nautic_section_subtitle"
    },
    {
      "name": "faq_explore_h3_timing",
      "level": 3,
      "text": "Combien de temps pour naviguer jusqu’à Saleccia ?",
      "style": "ma_nautic_section_subtitle"
    },
    {
      "name": "faq_explore_h3_swim",
      "level": 3,
      "text": "Peut-on se baigner dans les criques des Agriates ?",
      "style": "ma_nautic_section_subtitle"
    },
    {
      "name": "faq_services_h2",
      "level": 2,
      "text": "Services sur place et à bord",
      "style": "ma_nautic_section_title"
    },
    {
      "name": "faq_services_h3_agriates",
      "level": 3,
      "text": "Y a-t-il des restaurants ou paillotes dans les Agriates ?",
      "style": "ma_nautic_section_subtitle"
    },
    {
      "name": "faq_services_h3_saleccia",
      "level": 3,
      "text": "Faut-il réserver pour manger sur la plage de Saleccia ?",
      "style": "ma_nautic_section_subtitle"
    },
    {
      "name": "faq_number_h2",
      "level": 2,
      "text": "Choisir son bateau selon le nombre de passagers",
      "style": "ma_nautic_section_title"
    },
    {
      "name": "faq_number_h3_four",
      "level": 3,
      "text": "Quel bateau louer pour 4 personnes ?",
      "style": "ma_nautic_section_subtitle"
    },
    {
      "name": "faq_number_h3_six",
      "level": 3,
      "text": "Quel modèle choisir pour 6 personnes ?",
      "style": "ma_nautic_section_subtitle"
    },
    {
      "name": "faq_number_h3_ten",
      "level": 3,
      "text": "Quelle unité pour un groupe de 10 personnes ?",
      "style": "ma_nautic_section_subtitle"
    },
    {
      "name": "faq_number_h3_children",
      "level": 3,
      "text": "Les enfants peuvent-ils embarquer en toute sécurité ?",
      "style": "ma_nautic_section_subtitle"
    },
    {
      "name": "faq_activity_h2",
      "level": 2,
      "text": "Activités nautiques à Saint-Florent",
      "style": "ma_nautic_section_title"
    },
    {
      "name": "faq_activity_h3_nautical",
      "level": 3,
      "text": "Quelles activités nautiques peut-on pratiquer avec MA Nautic ?",
      "style": "ma_nautic_section_subtitle"
    },
    {
      "name": "faq_activity_h3_wakeboard",
      "level": 3,
      "text": "Peut-on louer une bouée tractée ou un wakeboard ?",
      "style": "ma_nautic_section_subtitle"
    },
    {
      "name": "faq_activity_h3_children",
      "level": 3,
      "text": "Les activités nautiques sont-elles adaptées aux enfants ?",
      "style": "ma_nautic_section_subtitle"
    },
    {
      "name": "faq_need_h2",
      "level": 2,
      "text": "Naviguer en Haute Corse : ce qu’il faut savoir avant de partir",
      "style": "ma_nautic_section_title"
    },
    {
      "name": "faq_information_h2",
      "level": 2,
      "text": "Infos pratiques – MA Nautic",
      "style": "ma_nautic_section_title"
    },
    {
      "name": "legal_h1",
      "level": 1,
      "text": "CRÉDITS & MENTIONS LÉGALES - M.A NAUTIC",
      "style": "ma_nautic_section_drop"
    },
    {
      "name": "legal_info_h2",
      "level": 2,
      "text": "Informations légales et éditeur du site",
      "style": "ma_nautic_section_title"
    },
    {
      "name": "legal_info_h3_host",
      "level": 3,
      "text": "Hébergeur du site",
      "style": "ma_nautic_section_subtitle"
    },
    {
      "name": "legal_info_h3_publisher",
      "level": 3,
      "text": "Éditeur du site",
      "style": "ma_nautic_section_subtitle"
    },
    {
      "name": "legal_mediation_h2",
      "level": 2,
      "text": "Informations légales et éditeur du site",
      "style": "ma_nautic_section_title"
    },
    {
      "name": "legal_mediation_h3_consumer",
      "level": 3,
      "text": "Médiation à la consommation",
      "style": "ma_nautic_section_subtitle"
    },
    {
      "name": "legal_mediation_h3_resolution",
      "level": 3,
      "text": "Règlement des litiges",
      "style": "ma_nautic_section_subtitle"
    },
    {
      "name": "legal_use_h2",
      "level": 2,
      "text": "Conditions d'utilisation du site",
      "style": "ma_nautic_section_title"
    },
    {
      "name": "legal_use_h3_access",
      "level": 3,
      "text": "Accès et utilisation du site",
      "style": "ma_nautic_section_subtitle"
    },
    {
      "name": "legal_use_h3_liability",
      "level": 3,
      "text": "Limitation de responsabilité",
      "style": "ma_nautic_section_subtitle"
    },
    {
      "name": "legal_data_h2",
      "level": 2,
      "text": "Protection des données personnelles",
      "style": "ma_nautic_section_title"
    },
    {
      "name": "legal_data_h3_collection",
      "level": 3,
      "text": "Collecte et utilisation des données personnelles",
      "style": "ma_nautic_section_subtitle"
    },
    {
      "name": "legal_data_h3_rights",
      "level": 3,
      "text": "Droits d'accès, de rectification et de suppression",
      "style": "ma_nautic_section_subtitle"
    },
    {
      "name": "legal_data_h3_cookies",
      "level": 3,
      "text": "Cookies",
      "style": "ma_nautic_section_subtitle"
    },
    {
      "name": "legal_property_h2",
      "level": 2,
      "text": "Propriété intellectuelle",
      "style": "ma_nautic_section_title"
    },
    {
      "name": "legal_property_h3_copyright",
      "level": 3,
      "text": "Droits d'auteur et propriété du contenu",
      "style": "ma_nautic_section_subtitle"
    },
    {
      "name": "legal_management_h2",
      "level": 2,
      "text": "Prestataire technique et gestion des services",
      "style": "ma_nautic_section_title"
    },
    {
      "name": "legal_management_h3_technical",
      "level": 3,
      "text": "Prestataire technique",
      "style": "ma_nautic_section_subtitle"
    },
    {
      "name": "boat_alba",
      "level": 2,
      "text": "Alba",
      "style": "ma_nautic_section_subtitle"
    },
    {
      "name": "camarat_cc",
      "level": 2,
      "text": "Cap Camarat 5.5 style",
      "style": "ma_nautic_subtitle_boat"
    },
    {
      "name": "boat_nine",
      "level": 3,
      "text": "Nine",
      "style": "ma_nautic_section_subtitle"
    },
    {
      "name": "capelli_500",
      "level": 2,
      "text": "Capelli Tempest 500",
      "style": "ma_nautic_subtitle_boat"
    },
    {
      "name": "boat_first",
      "level": 3,
      "text": "First",
      "style": "ma_nautic_section_subtitle"
    },
    {
      "name": "capelli_630",
      "level": 2,
      "text": "Capelli Tempest 630",
      "style": "ma_nautic_subtitle_boat"
    },
    {
      "name": "boat_enzo",
      "level": 3,
      "text": "Enzo",
      "style": "ma_nautic_section_subtitle"
    },
    {
      "name": "motonautica_780",
      "level": 2,
      "text": "Motonautica Vesuviana 780 confort",
      "style": "ma_nautic_subtitle_boat"
    },
    {
      "name": "boat_libecciu",
      "level": 3,
      "text": "Libecciu",
      "style": "ma_nautic_section_subtitle"
    },
    {
      "name": "capelli_700",
      "level": 2,
      "text": "Capelli Tempest 700",
      "style": "ma_nautic_subtitle_boat"
    },
    {
      "name": "boat_casablanca",
      "level": 3,
      "text": "Casa Blanca",
      "style": "ma_nautic_section_subtitle"
    },
    {
      "name": "lomac_850",
      "level": 2,
      "text": "Lomac 850",
      "style": "ma_nautic_subtitle_boat"
    },
    {
      "name": "location_bateaux",
      "text": "LOCATION DE BATEAUX",
      "level": 1,
      "style": "ma_nautic_main_title"
    },
    {
      "name": "golfe_st_florent",
      "text": "Golfe de St Florent",
      "level": 2,
      "style": "ma_nautic_subtitle"
    },
    {
      "name": "ma_info",
      "level": 2,
      "text": "INFORMATIONS",
      "style": "ma_nautic_subtitle_light"
    },
    {
      "name": "ma_options",
      "level": 2,
      "text": "OPTIONS",
      "style": "ma_nautic_subtitle_light"
    }
  ]
}